Metadata-Version: 1.0
Name: distributions697
Version: 0.1
Summary: Gaussian distributions
Home-page: UNKNOWN
Author: Alexander Hepel
Author-email: UNKNOWN
License: UNKNOWN
Platform: UNKNOWN
